[
	{"drawDate": "03-01-2024", "one" : "33*26", "two" : "18*39", "three" : "21*14"},
	{"drawDate": "03-02-2024", "one" : "11*32", "two" : "27*32", "three" : "23*39"},
	{"drawDate": "03-03-2024", "one" : "32*16", "two" : "39*22", "three" : "07*01"},
	{"drawDate": "03-04-2024", "one" : "26*18", "two" : "01*10", "three" : "07*10"},
	{"drawDate": "03-05-2024", "one" : "11*18", "two" : "10*23", "three" : "07*16"},
	{"drawDate": "03-06-2024", "one" : "15*30", "two" : "11*11", "three" : "03*25"},
	{"drawDate": "03-07-2024", "one" : "17*27", "two" : "22*09", "three" : "01*11"},
	{"drawDate": "03-08-2024", "one" : "35*04", "two" : "20*36", "three" : "33*35"},
	{"drawDate": "03-09-2024", "one" : "15*08", "two" : "", "three" : ""}
]
